Workbook

Sheet Огляд
A1: Datadog (NASDAQ: DDOG) — Cash Flow навчальний файл
A3: FY2021–FY2025 | USD млн | актуально за Form 10-K, поданим 18 лютого 2026 року
A5: ЧЕКЛИСТ ДО УРОКУ
A6: Статус | B6: Завдання | D6: Ваші нотатки / відповідь після аналізу (сині клітинки можна редагувати)
A7: Не розпочато | B7: Знайти cash flow statement компанії і пройтись по 3 блоках
A8: Не розпочато | B8: Порахувати free cash flow і подивитись його динаміку за кілька років
A9: Не розпочато | B9: Порівняти operating cash flow з чистим прибутком — чи немає розриву
A12: КЛЮЧОВІ ПОКАЗНИКИ FY2025
A13: Operating cash flow | E13: Datadog free cash flow | I13: Розрив OCF − Net income | M13: FCF CAGR 2021–2025
A16: =Дані!H10 -> 1050.135 | E16: =FCF!F11 -> 914.717 | I16: ='OCF vs NI'!F8 -> 942.394 | M16: =FCF!B17 -> 0.38232794
A20: ЩО ВИДНО З ТРЬОХ БЛОКІВ | I20: ГОЛОВНИЙ ВИСНОВОК
A21: • Операції: OCF зростав щороку й у 2025 перевищив $1,05 млрд. • Інвестиції: CFI у 2025 становив −$1,33 млрд, переважно через marketable securities, M&A та більші інвестиції у ПЗ/PP&E. • Фінансування: після великого припливу у 2024 ($787,1 млн) у 2025 відтік склав −$572,5 млн через погашення конвертованих нот і відсутність повторення випуску боргу. | I21: Datadog має сильну динаміку OCF і FCF, але великий розрив із GAAP net income значною мірою створює stock-based compensation. Тому позитивний cash flow варто читати разом із SBC, розмиванням, deferred revenue та капіталізованою розробкою ПЗ.
I32: Рік | J32: Operating cash flow | K32: Datadog FCF | L32: Net income | M32: SBC
I33: 2021 | J33: ='Cash Flow'!B11 -> 286.545 | K33: =FCF!B11 -> 250.52 | L33: ='OCF vs NI'!B6 -> -20.745 | M33: ='OCF vs NI'!B10 -> 163.737
I34: 2022 | J34: ='Cash Flow'!C11 -> 418.407 | K34: =FCF!C11 -> 353.518 | L34: ='OCF vs NI'!C6 -> -50.16 | M34: ='OCF vs NI'!C10 -> 363.154
I35: 2023 | J35: ='Cash Flow'!D11 -> 659.954 | K35: =FCF!D11 -> 597.548 | L35: ='OCF vs NI'!D6 -> 48.568 | M35: ='OCF vs NI'!D10 -> 482.3
I36: 2024 | J36: ='Cash Flow'!E11 -> 870.603 | K36: =FCF!E11 -> 775.103 | L36: ='OCF vs NI'!E6 -> 183.746 | M36: ='OCF vs NI'!E10 -> 570.336
I37: 2025 | J37: ='Cash Flow'!F11 -> 1050.135 | K37: =FCF!F11 -> 914.717 | L37: ='OCF vs NI'!F6 -> 107.741 | M37: ='OCF vs NI'!F10 -> 750.671
I40: Рік | J40: Operating | K40: Investing | L40: Financing | M40: FX | N40: Net change
I41: 2021 | J41: ='Cash Flow'!B11 -> 286.545 | K41: ='Cash Flow'!B17 -> -273.74 | L41: ='Cash Flow'!B20 -> 34.94 | M41: ='Cash Flow'!B23 -> -1.993 | N41: ='Cash Flow'!B24 -> 45.752
I42: 2022 | J42: ='Cash Flow'!C11 -> 418.407 | K42: ='Cash Flow'!C17 -> -384.67 | L42: ='Cash Flow'!C20 -> 36.023 | M42: ='Cash Flow'!C23 -> -1.935 | N42: ='Cash Flow'!C24 -> 67.825
I43: 2023 | J43: ='Cash Flow'!D11 -> 659.954 | K43: ='Cash Flow'!D17 -> -731.365 | L43: ='Cash Flow'!D20 -> 58.279 | M43: ='Cash Flow'!D23 -> 1.183 | N43: ='Cash Flow'!D24 -> -11.949
I44: 2024 | J44: ='Cash Flow'!E11 -> 870.603 | K44: ='Cash Flow'!E17 -> -736.84 | L44: ='Cash Flow'!E20 -> 787.083 | M44: ='Cash Flow'!E23 -> -4.202 | N44: ='Cash Flow'!E24 -> 916.644
I45: 2025 | J45: ='Cash Flow'!F11 -> 1050.135 | K45: ='Cash Flow'!F17 -> -1334.48 | L45: ='Cash Flow'!F20 -> -572.483 | M45: ='Cash Flow'!F23 -> 11.15 | N45: ='Cash Flow'!F24 -> -845.678

Sheet Cash Flow
A1: Cash Flow Statement — 3 блоки
A3: Навчальна декомпозиція. Зелений шрифт = посилання на інший аркуш; чорний = формула на цьому аркуші.
A5: Метрика | B5: 2021 | C5: 2022 | D5: 2023 | E5: 2024 | F5: 2025 | G5: Як читати / що сталося у 2025
A6: 1. ОПЕРАЦІЙНА ДІЯЛЬНІСТЬ — чи генерує основний бізнес готівку?
A7: Net income (loss) | B7: =Дані!D7 -> -20.745 | C7: =Дані!E7 -> -50.16 | D7: =Дані!F7 -> 48.568 | E7: =Дані!G7 -> 183.746 | F7: =Дані!H7 -> 107.741
A8: Depreciation & amortization | B8: =Дані!D8 -> 22.938 | C8: =Дані!E8 -> 34.629 | D8: =Дані!F8 -> 44.465 | E8: =Дані!G8 -> 54.933 | F8: =Дані!H8 -> 55.756
A9: Stock-based compensation | B9: =Дані!D9 -> 163.737 | C9: =Дані!E9 -> 363.154 | D9: =Дані!F9 -> 482.3 | E9: =Дані!G9 -> 570.336 | F9: =Дані!H9 -> 750.671
A10: Інші негрошові коригування та зміни оборотного капіталу | B10: =Дані!D10-SUM(B7:B9) -> 120.615 | C10: =Дані!E10-SUM(C7:C9) -> 70.784 | D10: =Дані!F10-SUM(D7:D9) -> 84.621 | E10: =Дані!G10-SUM(E7:E9) -> 61.588 | F10: =Дані!H10-SUM(F7:F9) -> 135.967
A11: Net cash provided by operating activities (OCF) | B11: =Дані!D10 -> 286.545 | C11: =Дані!E10 -> 418.407 | D11: =Дані!F10 -> 659.954 | E11: =Дані!G10 -> 870.603 | F11: =Дані!H10 -> 1050.135 | G11: OCF зріс на $179,5 млн. Основний плюс — більші негрошові витрати (передусім SBC), deferred revenue та accrued liabilities; частково нівельовано зростанням A/R і deferred contract costs.
A13: 2. ІНВЕСТИЦІЙНА ДІЯЛЬНІСТЬ — куди компанія вкладає готівку?
A14: Purchases of property & equipment | B14: =Дані!D13 -> -9.956 | C14: =Дані!E13 -> -35.261 | D14: =Дані!F13 -> -27.586 | E14: =Дані!G13 -> -34.719 | F14: =Дані!H13 -> -49.578
A15: Capitalized software development costs | B15: =Дані!D14 -> -26.069 | C15: =Дані!E14 -> -29.628 | D15: =Дані!F14 -> -34.82 | E15: =Дані!G14 -> -60.781 | F15: =Дані!H14 -> -85.84
A16: Інші інвестиції (ринкові цінні папери, M&A тощо) | B16: =Дані!D11-SUM(B14:B15) -> -237.715 | C16: =Дані!E11-SUM(C14:C15) -> -319.781 | D16: =Дані!F11-SUM(D14:D15) -> -668.959 | E16: =Дані!G11-SUM(E14:E15) -> -641.34 | F16: =Дані!H11-SUM(F14:F15) -> -1199.062
A17: Net cash used in investing activities (CFI) | B17: =Дані!D11 -> -273.74 | C17: =Дані!E11 -> -384.67 | D17: =Дані!F11 -> -731.365 | E17: =Дані!G11 -> -736.84 | F17: =Дані!H11 -> -1334.48 | G17: CFI-відтік збільшився на $597,6 млн: більше купівель marketable securities, M&A, капіталізованого ПЗ та PP&E; частково компенсовано більшими погашеннями/продажами цінних паперів.
A19: 3. ФІНАНСОВА ДІЯЛЬНІСТЬ — як компанія залучає або повертає капітал?
A20: Net cash provided by / (used in) financing activities (CFF) | B20: =Дані!D12 -> 34.94 | C20: =Дані!E12 -> 36.023 | D20: =Дані!F12 -> 58.279 | E20: =Дані!G12 -> 787.083 | F20: =Дані!H12 -> -572.483 | G20: У 2025 CFF став від’ємним: погашення 2025 Notes і відсутність повторення великого випуску 2029 Notes, який підтримав 2024 рік.
A22: ЗВЕДЕННЯ РУХУ ГОТІВКИ
A23: Ефект валютних курсів (розрахунково) | B23: =Дані!D15-SUM(B11,B17,B20) -> -1.993 | C23: =Дані!E15-SUM(C11,C17,C20) -> -1.935 | D23: =Дані!F15-SUM(D11,D17,D20) -> 1.183 | E23: =Дані!G15-SUM(E11,E17,E20) -> -4.202 | F23: =Дані!H15-SUM(F11,F17,F20) -> 11.15
A24: Net increase / (decrease) in cash incl. FX | B24: =Дані!D15 -> 45.752 | C24: =Дані!E15 -> 67.825 | D24: =Дані!F15 -> -11.949 | E24: =Дані!G15 -> 916.644 | F24: =Дані!H15 -> -845.678
A25: Контроль: OCF + CFI + CFF + FX | B25: =SUM(B11,B17,B20,B23) -> 45.752 | C25: =SUM(C11,C17,C20,C23) -> 67.825 | D25: =SUM(D11,D17,D20,D23) -> -11.949 | E25: =SUM(E11,E17,E20,E23) -> 916.644 | F25: =SUM(F11,F17,F20,F23) -> -845.678

Sheet FCF
A1: Free Cash Flow — розрахунок і динаміка
A3: Datadog FCF (non-GAAP) = OCF − PP&E purchases − capitalized software development. Класичний FCF нижче показано для порівняння дефініцій.
A5: Метрика | B5: 2021 | C5: 2022 | D5: 2023 | E5: 2024 | F5: 2025 | H5: Рік | I5: Operating cash flow | J5: Datadog FCF | K5: Net income
A6: Revenue | B6: =Дані!D6 -> 1028.784 | C6: =Дані!E6 -> 1675.1 | D6: =Дані!F6 -> 2128.359 | E6: =Дані!G6 -> 2684.275 | F6: =Дані!H6 -> 3427.158 | H6: 2021 | I6: =B7 -> 286.545 | J6: =B11 -> 250.52 | K6: =Дані!D7 -> -20.745
A7: Operating cash flow | B7: =Дані!D10 -> 286.545 | C7: =Дані!E10 -> 418.407 | D7: =Дані!F10 -> 659.954 | E7: =Дані!G10 -> 870.603 | F7: =Дані!H10 -> 1050.135 | H7: 2022 | I7: =C7 -> 418.407 | J7: =C11 -> 353.518 | K7: =Дані!E7 -> -50.16
A8: Less: PP&E purchases | B8: =Дані!D13 -> -9.956 | C8: =Дані!E13 -> -35.261 | D8: =Дані!F13 -> -27.586 | E8: =Дані!G13 -> -34.719 | F8: =Дані!H13 -> -49.578 | H8: 2023 | I8: =D7 -> 659.954 | J8: =D11 -> 597.548 | K8: =Дані!F7 -> 48.568
A9: Класичний FCF = OCF − PP&E capex | B9: =SUM(B7:B8) -> 276.589 | C9: =SUM(C7:C8) -> 383.146 | D9: =SUM(D7:D8) -> 632.368 | E9: =SUM(E7:E8) -> 835.884 | F9: =SUM(F7:F8) -> 1000.557 | H9: 2024 | I9: =E7 -> 870.603 | J9: =E11 -> 775.103 | K9: =Дані!G7 -> 183.746
A10: Less: Capitalized software development | B10: =Дані!D14 -> -26.069 | C10: =Дані!E14 -> -29.628 | D10: =Дані!F14 -> -34.82 | E10: =Дані!G14 -> -60.781 | F10: =Дані!H14 -> -85.84 | H10: 2025 | I10: =F7 -> 1050.135 | J10: =F11 -> 914.717 | K10: =Дані!H7 -> 107.741
A11: Datadog FCF (company definition) | B11: =SUM(B7:B8,B10) -> 250.52 | C11: =SUM(C7:C8,C10) -> 353.518 | D11: =SUM(D7:D8,D10) -> 597.548 | E11: =SUM(E7:E8,E10) -> 775.103 | F11: =SUM(F7:F8,F10) -> 914.717
A12: FCF margin | B12: =B11/B6 -> 0.24351079 | C12: =C11/C6 -> 0.21104292 | D12: =D11/D6 -> 0.28075527 | E12: =E11/E6 -> 0.28875693 | F12: =F11/F6 -> 0.26690249
A15: ДИНАМІКА ТА КОНТРОЛЬ
A16: YoY growth — Datadog FCF | C16: =C11/B11-1 -> 0.41113684 | D16: =D11/C11-1 -> 0.69029017 | E16: =E11/D11-1 -> 0.29713931 | F16: =F11/E11-1 -> 0.18012316
A17: CAGR 2021–2025 | B17: =(F11/B11)^(1/4)-1 -> 0.38232794
A18: Різниця: класичний FCF − Datadog FCF | B18: =B9-B11 -> 26.069 | C18: =C9-C11 -> 29.628 | D18: =D9-D11 -> 34.82 | E18: =E9-E11 -> 60.781 | F18: =F9-F11 -> 85.84
A19: Контроль vs company-reported FCF | B19: =ROUND(B11-Дані!D17,3) -> 0 | C19: =ROUND(C11-Дані!E17,3) -> 0 | D19: =ROUND(D11-Дані!F17,3) -> 0 | E19: =ROUND(E11-Дані!G17,3) -> 0 | F19: =ROUND(F11-Дані!H17,3) -> 0
A22: КЛЮЧОВИЙ ВИСНОВОК
A23: FCF Datadog зріс із $250,5 млн у 2021 до $914,7 млн у 2025 (CAGR ≈ 38%). Маржа FCF у 2025 становить близько 26,7%. Водночас компанійна дефініція є суворішою за простий OCF − PP&E capex, бо додатково віднімає капіталізовану розробку ПЗ.

Sheet OCF vs NI
A1: Operating Cash Flow vs Net Income
A3: Мета: побачити, чи немає розриву між бухгалтерським прибутком і грошовим потоком — та зрозуміти, що саме створює розрив.
A5: Метрика | B5: 2021 | C5: 2022 | D5: 2023 | E5: 2024 | F5: 2025 | H5: Рік | I5: Operating cash flow | J5: Net income | K5: SBC
A6: Net income (loss) | B6: =Дані!D7 -> -20.745 | C6: =Дані!E7 -> -50.16 | D6: =Дані!F7 -> 48.568 | E6: =Дані!G7 -> 183.746 | F6: =Дані!H7 -> 107.741 | H6: 2021 | I6: =B7 -> 286.545 | J6: =B6 -> -20.745 | K6: =B10 -> 163.737
A7: Operating cash flow | B7: =Дані!D10 -> 286.545 | C7: =Дані!E10 -> 418.407 | D7: =Дані!F10 -> 659.954 | E7: =Дані!G10 -> 870.603 | F7: =Дані!H10 -> 1050.135 | H7: 2022 | I7: =C7 -> 418.407 | J7: =C6 -> -50.16 | K7: =C10 -> 363.154
A8: Розрив: OCF − Net income | B8: =B7-B6 -> 307.29 | C8: =C7-C6 -> 468.567 | D8: =D7-D6 -> 611.386 | E8: =E7-E6 -> 686.857 | F8: =F7-F6 -> 942.394 | H8: 2023 | I8: =D7 -> 659.954 | J8: =D6 -> 48.568 | K8: =D10 -> 482.3
A9: OCF / Net income (лише коли NI > 0) | B9: =IF(B6>0,B7/B6,"") | C9: =IF(C6>0,C7/C6,"") | D9: =IF(D6>0,D7/D6,"") -> 13.588247 | E9: =IF(E6>0,E7/E6,"") -> 4.7380787 | F9: =IF(F6>0,F7/F6,"") -> 9.7468466 | H9: 2024 | I9: =E7 -> 870.603 | J9: =E6 -> 183.746 | K9: =E10 -> 570.336
A10: Stock-based compensation | B10: =Дані!D9 -> 163.737 | C10: =Дані!E9 -> 363.154 | D10: =Дані!F9 -> 482.3 | E10: =Дані!G9 -> 570.336 | F10: =Дані!H9 -> 750.671 | H10: 2025 | I10: =F7 -> 1050.135 | J10: =F6 -> 107.741 | K10: =F10 -> 750.671
A11: SBC як % розриву | B11: =B10/B8 -> 0.53284194 | C11: =C10/C8 -> 0.77503111 | D11: =D10/D8 -> 0.78886334 | E11: =E10/E8 -> 0.83035625 | F11: =F10/F8 -> 0.79655749
A12: Розрив після виключення SBC | B12: =B8-B10 -> 143.553 | C12: =C8-C10 -> 105.413 | D12: =D8-D10 -> 129.086 | E12: =E8-E10 -> 116.521 | F12: =F8-F10 -> 191.723
A15: ІНТЕРПРЕТАЦІЯ
A16: Розрив є великим і позитивним: OCF суттєво перевищує GAAP net income в усі роки. Це не автоматично означає «високу якість прибутку»: у 2025 близько 79,7% розриву пояснюється stock-based compensation — негрошовою витратою, яка додається назад у cash flow statement, але може розмивати акціонерів.
A21: Після виключення SBC розрив залишається позитивним ($191,7 млн у 2025), але значно меншим. Практичний висновок: дивись одночасно на OCF/FCF, динаміку SBC, deferred revenue, accounts receivable і капіталізоване ПЗ.

Sheet Дані
A1: Datadog — історичні вхідні дані
A3: USD млн; FY закінчується 31 грудня. Значення імпортовані з 10-K / SEC Companyfacts і не є редагованими припущеннями.
A5: Метрика | B5: Одиниці | C5: Source ID | D5: 2021 | E5: 2022 | F5: 2023 | G5: 2024 | H5: 2025 | I5: XBRL tag / визначення
A6: Revenue | B6: USD млн | C6: SRC-001 / SRC-002 | D6: 1028.784 | E6: 1675.1 | F6: 2128.359 | G6: 2684.275 | H6: 3427.158 | I6: RevenueFromContractWithCustomerExcludingAssessedTax
A7: Net income (loss) | B7: USD млн | C7: SRC-001 / SRC-002 | D7: -20.745 | E7: -50.16 | F7: 48.568 | G7: 183.746 | H7: 107.741 | I7: NetIncomeLoss
A8: Depreciation & amortization | B8: USD млн | C8: SRC-001 / SRC-002 | D8: 22.938 | E8: 34.629 | F8: 44.465 | G8: 54.933 | H8: 55.756 | I8: DepreciationAndAmortization
A9: Stock-based compensation, net of amounts capitalized | B9: USD млн | C9: SRC-001 / SRC-002 | D9: 163.737 | E9: 363.154 | F9: 482.3 | G9: 570.336 | H9: 750.671 | I9: AllocatedShareBasedCompensationExpense
A10: Net cash provided by operating activities | B10: USD млн | C10: SRC-001 / SRC-002 | D10: 286.545 | E10: 418.407 | F10: 659.954 | G10: 870.603 | H10: 1050.135 | I10: NetCashProvidedByUsedInOperatingActivities
A11: Net cash used in investing activities | B11: USD млн | C11: SRC-001 / SRC-002 | D11: -273.74 | E11: -384.67 | F11: -731.365 | G11: -736.84 | H11: -1334.48 | I11: NetCashProvidedByUsedInInvestingActivities
A12: Net cash provided by / (used in) financing activities | B12: USD млн | C12: SRC-001 / SRC-002 | D12: 34.94 | E12: 36.023 | F12: 58.279 | G12: 787.083 | H12: -572.483 | I12: NetCashProvidedByUsedInFinancingActivities
A13: Purchases of property & equipment | B13: USD млн | C13: SRC-001 / SRC-002 | D13: -9.956 | E13: -35.261 | F13: -27.586 | G13: -34.719 | H13: -49.578 | I13: PaymentsToAcquirePropertyPlantAndEquipment
A14: Capitalized software development costs | B14: USD млн | C14: SRC-001 / SRC-002 | D14: -26.069 | E14: -29.628 | F14: -34.82 | G14: -60.781 | H14: -85.84 | I14: PaymentsToDevelopSoftware
A15: Net increase / (decrease) in cash incl. FX | B15: USD млн | C15: SRC-001 / SRC-002 | D15: 45.752 | E15: 67.825 | F15: -11.949 | G15: 916.644 | H15: -845.678 | I15: CashCashEquivalents…IncreaseDecreaseIncludingExchangeRateEffect
A16: Cash & cash equivalents — end of period | B16: USD млн | C16: SRC-001 / SRC-002 | D16: 270.973 | E16: 338.985 | F16: 330.339 | G16: 1246.983 | H16: 401.305 | I16: CashAndCashEquivalentsAtCarryingValue
A17: Company-reported non-GAAP free cash flow | B17: USD млн | C17: SRC-001 / SRC-002 | D17: 250.52 | E17: 353.518 | F17: 597.548 | G17: 775.103 | H17: 914.717 | I17: OCF − PP&E purchases − capitalized software development

Sheet Перевірки
A1: Перевірки моделі
A3: Кожна перевірка має окремі очікуване значення, фактичне значення, відхилення, допуск і статус.
A5: Check ID | B5: Область | C5: Період | D5: Очікуване | E5: Фактичне | F5: Різниця | G5: Допуск | H5: Статус
A6: CF-1 | B6: 3-block cash flow tie | C6: 2021 | D6: ='Cash Flow'!B24 -> 45.752 | E6: ='Cash Flow'!B25 -> 45.752 | F6: =ROUND(E6-D6,3) -> 0 | G6: 0.01 | H6: =IF(ABS(F6)<=G6,"OK","CHECK") -> OK
A7: CF-2 | B7: 3-block cash flow tie | C7: 2022 | D7: ='Cash Flow'!C24 -> 67.825 | E7: ='Cash Flow'!C25 -> 67.825 | F7: =ROUND(E7-D7,3) -> 0 | G7: 0.01 | H7: =IF(ABS(F7)<=G7,"OK","CHECK") -> OK
A8: CF-3 | B8: 3-block cash flow tie | C8: 2023 | D8: ='Cash Flow'!D24 -> -11.949 | E8: ='Cash Flow'!D25 -> -11.949 | F8: =ROUND(E8-D8,3) -> 0 | G8: 0.01 | H8: =IF(ABS(F8)<=G8,"OK","CHECK") -> OK
A9: CF-4 | B9: 3-block cash flow tie | C9: 2024 | D9: ='Cash Flow'!E24 -> 916.644 | E9: ='Cash Flow'!E25 -> 916.644 | F9: =ROUND(E9-D9,3) -> 0 | G9: 0.01 | H9: =IF(ABS(F9)<=G9,"OK","CHECK") -> OK
A10: CF-5 | B10: 3-block cash flow tie | C10: 2025 | D10: ='Cash Flow'!F24 -> -845.678 | E10: ='Cash Flow'!F25 -> -845.678 | F10: =ROUND(E10-D10,3) -> 0 | G10: 0.01 | H10: =IF(ABS(F10)<=G10,"OK","CHECK") -> OK
A13: FCF-1 | B13: Datadog FCF tie | C13: 2021 | D13: =Дані!D17 -> 250.52 | E13: =FCF!B11 -> 250.52 | F13: =ROUND(E13-D13,3) -> 0 | G13: 0.01 | H13: =IF(ABS(F13)<=G13,"OK","CHECK") -> OK
A14: FCF-2 | B14: Datadog FCF tie | C14: 2022 | D14: =Дані!E17 -> 353.518 | E14: =FCF!C11 -> 353.518 | F14: =ROUND(E14-D14,3) -> 0 | G14: 0.01 | H14: =IF(ABS(F14)<=G14,"OK","CHECK") -> OK
A15: FCF-3 | B15: Datadog FCF tie | C15: 2023 | D15: =Дані!F17 -> 597.548 | E15: =FCF!D11 -> 597.548 | F15: =ROUND(E15-D15,3) -> 0 | G15: 0.01 | H15: =IF(ABS(F15)<=G15,"OK","CHECK") -> OK
A16: FCF-4 | B16: Datadog FCF tie | C16: 2024 | D16: =Дані!G17 -> 775.103 | E16: =FCF!E11 -> 775.103 | F16: =ROUND(E16-D16,3) -> 0 | G16: 0.01 | H16: =IF(ABS(F16)<=G16,"OK","CHECK") -> OK
A17: FCF-5 | B17: Datadog FCF tie | C17: 2025 | D17: =Дані!H17 -> 914.717 | E17: =FCF!F11 -> 914.717 | F17: =ROUND(E17-D17,3) -> 0 | G17: 0.01 | H17: =IF(ABS(F17)<=G17,"OK","CHECK") -> OK
A20: SRC-1 | B20: Source IDs complete | C20: 2021–2025 | D20: 12 | E20: =COUNTIF(Дані!C6:C17,"<>") -> 12 | F20: =E20-D20 -> 0 | G20: 0 | H20: =IF(F20=0,"OK","CHECK") -> OK
A23: ЗАГАЛЬНИЙ СТАТУС
A24: Модель проходить, якщо всі 11 перевірок мають статус OK. | G24: =IF(COUNTIF(H6:H20,"CHECK")=0,"OK","CHECK") -> OK

Sheet Джерела
A1: Джерела та методологія
A3: Первинні публічні джерела. Повні URL наведені як plain text для аудиту.
A5: Source ID | B5: Назва | C5: Тип | D5: Періоди | E5: As-of / filing date | F5: Retrieved | G5: Rank | H5: Freshness | I5: Location / URL | J5: Примітка
A6: SRC-001 | B6: Datadog FY2025 Form 10-K | C6: filing | D6: FY2023–FY2025 | E6: 46071 | F6: 46232 | G6: 3 | H6: current | I6: https://www.sec.gov/Archives/edgar/data/1561550/000162828026008819/ddog-20251231.htm | J6: Statements of operations and cash flows; MD&A cash-flow summary; non-GAAP FCF reconciliation (pp. 54–58 / financial statements p. 66).
A7: SRC-002 | B7: Datadog FY2023 Form 10-K | C7: filing | D7: FY2021–FY2023 | E7: 45345 | F7: 46232 | G7: 3 | H7: acceptable_for_period | I7: https://www.sec.gov/Archives/edgar/data/1561550/000156155024000009/ddog-20231231.htm | J7: Historical 2021–2023 statements and FCF reconciliation; used because those periods are directly reported together.
A8: SRC-003 | B8: SEC Companyfacts API — CIK 0001561550 | C8: web / structured filing data | D8: FY2021–FY2025 | E8: 46071 | F8: 46232 | G8: 3 | H8: current | I8: https://data.sec.gov/api/xbrl/companyfacts/CIK0001561550.json | J8: Used to cross-check XBRL tags, units and annual values against the rendered filings.
A11: МЕТОДОЛОГІЯ
A12: Усі суми нормалізовані з USD тис. до USD млн. Cash-flow outflows збережені зі знаком мінус. FCF Datadog — non-GAAP показник компанії; він не обов’язково порівнюваний із FCF інших емітентів. SBC — негрошове коригування OCF, але економічно може спричиняти розмивання, тому його винесено окремо.
